.gitignore
Dockerfile
LICENSE
README.md
create_h5ad.py
logo.jpg
requirement.install.sh
setup.py
daism/__init__.py
daism/daism.py
daism.egg-info/PKG-INFO
daism.egg-info/SOURCES.txt
daism.egg-info/dependency_links.txt
daism.egg-info/entry_points.txt
daism.egg-info/requires.txt
daism.egg-info/top_level.txt
daism/modules/__init__.py
daism/modules/prediction.py
daism/modules/simulation.py
daism/modules/training.py
example/caliexp.txt
example/califra.txt
example/testexp.txt
example/testfra.txt