Metadata-Version: 1.2
Name: daism
Version: 2.0.3
Summary: Highly accurate cell type proportion estimation within silicodata augmentation and deep neural net-works
Home-page: https://github.com/xmuyulab/DAISM-XMBD
Author: zoelin
Author-email: linyating@stu.xmu.edu.cn
License: MIT License
Keywords: bioinformatics,data augmentation,in silico mixing,deep learning,single cell sequencing,deconvolution
Platform: UNKNOWN
Requires-Python: >3.7.0
